midi_manager/__init__.py
midi_manager/midi_manager.py
midi_manager-2.0.dist-info/DESCRIPTION.rst
midi_manager-2.0.dist-info/METADATA
midi_manager-2.0.dist-info/RECORD
midi_manager-2.0.dist-info/WHEEL
midi_manager-2.0.dist-info/metadata.json
midi_manager-2.0.dist-info/top_level.txt
