Metadata-Version: 2.0
Name: midi-manager
Version: 2.0
Summary: A python library to clean, process and convert midi datasets in ready to use formats like python lists, dictionaries and pickles for machine learning models
Home-page: https://github.com/sebasgverde/midi-manager
Author: Sebastian Garcia Valencia
Author-email: sebasgverde@gmail.com
License: MIT
Platform: UNKNOWN
Requires-Dist: MIDIUtil (>=1.1.3)
Requires-Dist: numpy (>=1.13.0)
Requires-Dist: python-midi (>=0.2.4)
